yew/__init__.py
yew/item.py
yew/npc.py
yew/player.py
yew/utils.py
yew-0.12.1.dist-info/METADATA
yew-0.12.1.dist-info/WHEEL
yew-0.12.1.dist-info/licenses/LICENSE
yew-0.12.1.dist-info/RECORD
