Metadata-Version: 2.4
Name: yew
Version: 0.12.1
Summary: An OldSchool RuneScape API wrapper for Python.
Project-URL: Homepage, https://github.com/bharat-nair/yew
Project-URL: Issues, https://github.com/bharat-nair/yew/issues
Author-email: Bharat Nair <bharat@rubberducker.xyz>
License-File: LICENSE
Classifier: Intended Audience :: Developers
Classifier: License :: OSI Approved :: MIT License
Classifier: Operating System :: OS Independent
Classifier: Programming Language :: Python :: 3
Classifier: Topic :: Games/Entertainment
Classifier: Topic :: Games/Entertainment :: Role-Playing
Classifier: Topic :: Internet
Classifier: Topic :: Software Development :: Libraries
Classifier: Topic :: Software Development :: Libraries :: Python Modules
Requires-Python: >=3.8
Requires-Dist: certifi==2024.2.2
Requires-Dist: charset-normalizer==3.3.2
Requires-Dist: idna==3.6
Requires-Dist: mwparserfromhell==0.6.6
Requires-Dist: requests==2.31.0
Requires-Dist: urllib3==2.2.1
